{
    "name": "Session",
    "fields": [
        {
            "fieldName": "thoughts",
            "fieldType": "byte[]",
            "fieldTypeBlobContent": "text",
            "fieldValidateRules": [
                "required"
            ]
        },
        {
            "fieldName": "date",
            "fieldType": "Instant",
            "fieldValidateRules": [
                "required"
            ]
        }
    ],
    "relationships": [
        {
            "relationshipType": "many-to-one",
            "otherEntityName": "project",
            "otherEntityRelationshipName": "session",
            "relationshipName": "project",
            "otherEntityField": "name"
        },
        {
            "relationshipType": "many-to-many",
            "otherEntityName": "tag",
            "otherEntityRelationshipName": "session",
            "relationshipName": "tag",
            "otherEntityField": "name",
            "ownerSide": true
        }
    ],
    "changelogDate": "20190716090235",
    "entityTableName": "session",
    "dto": "no",
    "pagination": "infinite-scroll",
    "service": "no",
    "jpaMetamodelFiltering": false,
    "fluentMethods": true,
    "clientRootFolder": "",
    "applications": "*"
}